{
  "last_updated": "2026-06-06T19:24:58.055759",
  "count": 41,
  "matches": [
    {
      "tournament": "Prostejov challenger",
      "time": "11:10",
      "player1": "Molcan A. (6)",
      "player2": "Barton H.",
      "odds1": 1.43,
      "odds2": 2.68,
      "tour": "ATP"
    },
    {
      "tournament": "Hertogenbosch",
      "time": "11:10",
      "player1": "Damm M. (3)",
      "player2": "Houkes M.",
      "odds1": 1.16,
      "odds2": 4.96,
      "tour": "ATP"
    },
    {
      "tournament": "Hertogenbosch",
      "time": "11:10",
      "player1": "Ficovich J. (8)",
      "player2": "Loof T.",
      "odds1": 1.08,
      "odds2": 7.08,
      "tour": "ATP"
    },
    {
      "tournament": "Stuttgart",
      "time": "11:10",
      "player1": "Onclin G. (7)",
      "player2": "Luz O.",
      "odds1": 1.03,
      "odds2": 12.0,
      "tour": "ATP"
    },
    {
      "tournament": "Stuttgart",
      "time": "11:10",
      "player1": "Huesler M.",
      "player2": "Basilashvili N. (3)",
      "odds1": 2.2,
      "odds2": 1.64,
      "tour": "ATP"
    },
    {
      "tournament": "Hertogenbosch",
      "time": "11:10",
      "player1": "Minnen G.",
      "player2": "Tomova V. (8)",
      "odds1": 1.26,
      "odds2": 3.65,
      "tour": "WTA"
    },
    {
      "tournament": "Hertogenbosch",
      "time": "11:10",
      "player1": "Volynets K. (3)",
      "player2": "Hibino N.",
      "odds1": 1.3,
      "odds2": 3.4,
      "tour": "WTA"
    },
    {
      "tournament": "Hertogenbosch",
      "time": "11:10",
      "player1": "Seidel E. (1)",
      "player2": "Liu C.",
      "odds1": 1.96,
      "odds2": 1.79,
      "tour": "WTA"
    },
    {
      "tournament": "Heilbronn challenger",
      "time": "12:10",
      "player1": "Nava E. (2)",
      "player2": "Squire H.",
      "odds1": 1.42,
      "odds2": 2.71,
      "tour": "ATP"
    },
    {
      "tournament": "Hertogenbosch",
      "time": "12:30",
      "player1": "Ymer E. (6)",
      "player2": "Visser M.",
      "odds1": 1.01,
      "odds2": 16.0,
      "tour": "ATP"
    },
    {
      "tournament": "Hertogenbosch",
      "time": "12:30",
      "player1": "Zhu L. (5)",
      "player2": "Lee C.",
      "odds1": 1.58,
      "odds2": 2.29,
      "tour": "WTA"
    },
    {
      "tournament": "Stuttgart",
      "time": "12:40",
      "player1": "Rodionov J. (5)",
      "player2": "Castelnuovo L.",
      "odds1": 1.16,
      "odds2": 5.05,
      "tour": "ATP"
    },
    {
      "tournament": "Stuttgart",
      "time": "12:40",
      "player1": "Shimabukuro S. (2)",
      "player2": "Sakellaridis S.",
      "odds1": 1.34,
      "odds2": 3.11,
      "tour": "ATP"
    },
    {
      "tournament": "Prostejov challenger",
      "time": "12:50",
      "player1": "Baez S. (1)",
      "player2": "Sanchez Izquierdo N.",
      "odds1": 1.24,
      "odds2": 3.81,
      "tour": "ATP"
    },
    {
      "tournament": "Hertogenbosch",
      "time": "13:00",
      "player1": "Vandewinkel H. (2)",
      "player2": "Barthel M.",
      "odds1": 1.35,
      "odds2": 3.06,
      "tour": "WTA"
    },
    {
      "tournament": "Centurion 2 challenger",
      "time": "13:10",
      "player1": "Donski A.",
      "player2": "Montsi K.",
      "odds1": 2.34,
      "odds2": 1.56,
      "tour": "ATP"
    },
    {
      "tournament": "Birmingham",
      "time": "13:10",
      "player1": "Eala A. (1)",
      "player2": "Masarova R.",
      "odds1": 1.59,
      "odds2": 2.28,
      "tour": "WTA"
    },
    {
      "tournament": "Birmingham",
      "time": "13:10",
      "player1": "Bartunkova N. (5)",
      "player2": "Krueger A.",
      "odds1": 2.36,
      "odds2": 1.56,
      "tour": "WTA"
    },
    {
      "tournament": "Heilbronn challenger",
      "time": "13:25",
      "player1": "Mikrut L.",
      "player2": "Dedura-Palomero D.",
      "odds1": 1.99,
      "odds2": 1.75,
      "tour": "ATP"
    },
    {
      "tournament": "Hertogenbosch",
      "time": "13:30",
      "player1": "Koevermans A. (7)",
      "player2": "Vrancken Peeters A.",
      "odds1": 1.37,
      "odds2": 2.96,
      "tour": "WTA"
    },
    {
      "tournament": "Stuttgart",
      "time": "13:55",
      "player1": "Herbert P.",
      "player2": "Glinka D. (6)",
      "odds1": 1.47,
      "odds2": 2.56,
      "tour": "ATP"
    },
    {
      "tournament": "Hertogenbosch",
      "time": "14:00",
      "player1": "Visker N.",
      "player2": "McDonald M. (4)",
      "odds1": 5.79,
      "odds2": 1.12,
      "tour": "ATP"
    },
    {
      "tournament": "Stuttgart",
      "time": "14:15",
      "player1": "Galarneau A. (8)",
      "player2": "Hsu Y.",
      "odds1": 1.57,
      "odds2": 2.31,
      "tour": "ATP"
    },
    {
      "tournament": "Hertogenbosch",
      "time": "14:20",
      "player1": "Jong S.",
      "player2": "Mochizuki S. (5)",
      "odds1": 3.3,
      "odds2": 1.31,
      "tour": "ATP"
    },
    {
      "tournament": "Hertogenbosch",
      "time": "14:35",
      "player1": "Montgomery R.",
      "player2": "Yuan Y. (4)",
      "odds1": 1.8,
      "odds2": 1.95,
      "tour": "WTA"
    },
    {
      "tournament": "Hertogenbosch",
      "time": "14:45",
      "player1": "Tomic B. (7)",
      "player2": "Deckers A.",
      "odds1": 1.3,
      "odds2": 3.35,
      "tour": "ATP"
    },
    {
      "tournament": "Hertogenbosch",
      "time": "15:00",
      "player1": "McCabe J.",
      "player2": "Wong C. (2)",
      "odds1": 2.22,
      "odds2": 1.62,
      "tour": "ATP"
    },
    {
      "tournament": "French Open",
      "time": "15:25",
      "player1": "Andreeva M. (8)",
      "player2": "Chwalinska M.",
      "odds1": 1.22,
      "odds2": 4.45,
      "tour": "WTA"
    },
    {
      "tournament": "Stuttgart",
      "time": "15:30",
      "player1": "Alkaya M.",
      "player2": "Sakellaridis M.",
      "odds1": 1.03,
      "odds2": 10.79,
      "tour": "ATP"
    },
    {
      "tournament": "Centurion 2 challenger",
      "time": "15:45",
      "player1": "Henning P. (6)",
      "player2": "Mayot H. (1)",
      "odds1": 2.01,
      "odds2": 1.75,
      "tour": "ATP"
    },
    {
      "tournament": "Hertogenbosch",
      "time": "16:00",
      "player1": "Bonzi B. (1)",
      "player2": "Polmans M.",
      "odds1": 1.14,
      "odds2": 5.22,
      "tour": "ATP"
    },
    {
      "tournament": "Hertogenbosch",
      "time": "16:15",
      "player1": "Garland J. (6)",
      "player2": "Du Pree B.",
      "odds1": 1.51,
      "odds2": 2.46,
      "tour": "WTA"
    },
    {
      "tournament": "Stuttgart",
      "time": "16:40",
      "player1": "Safiullin R. (4)",
      "player2": "Bar Biryukov P.",
      "odds1": 1.1,
      "odds2": 6.4,
      "tour": "ATP"
    },
    {
      "tournament": "Makarska",
      "time": "17:00",
      "player1": "Timofeeva M. (7)",
      "player2": "Sorribes Tormo S.",
      "odds1": 1.82,
      "odds2": 1.93,
      "tour": "WTA"
    },
    {
      "tournament": "Makarska",
      "time": "17:05",
      "player1": "Semenistaja D. (5)",
      "player2": "Avanesyan E.",
      "odds1": 1.95,
      "odds2": 1.81,
      "tour": "WTA"
    },
    {
      "tournament": "Foggia",
      "time": "17:50",
      "player1": "Grant T.",
      "player2": "Astakhova D.",
      "odds1": 1.34,
      "odds2": 3.16,
      "tour": "WTA"
    },
    {
      "tournament": "Perugia challenger",
      "time": "18:05",
      "player1": "Rocha H. (4)",
      "player2": "Skatov T.",
      "odds1": 1.5,
      "odds2": 2.47,
      "tour": "ATP"
    },
    {
      "tournament": "Tyler challenger",
      "time": "19:10",
      "player1": "Walton A. (1)",
      "player2": "Draxl L. (3)",
      "odds1": 1.47,
      "odds2": 2.71,
      "tour": "ATP"
    },
    {
      "tournament": "Tyler challenger",
      "time": "19:15",
      "player1": "Poling K.",
      "player2": "Ilagan A.",
      "odds1": 3.45,
      "odds2": 1.28,
      "tour": "ATP"
    },
    {
      "tournament": "Foggia",
      "time": "19:30",
      "player1": "Romero Gormaz L. (4)",
      "player2": "Bronzetti L. (8)",
      "odds1": 2.35,
      "odds2": 1.56,
      "tour": "WTA"
    },
    {
      "tournament": "Perugia challenger",
      "time": "20:40",
      "player1": "Merida Aguilar D. (3)",
      "player2": "Pellegrino A. (6)",
      "odds1": 1.64,
      "odds2": 2.16,
      "tour": "ATP"
    }
  ]
}