{
  "last_updated": "2026-07-14T02:33:26.981805",
  "count": 106,
  "matches": [
    {
      "tournament": "Lincoln challenger",
      "time": "00:40",
      "player1": "Shepp A.",
      "player2": "Kennedy J.",
      "odds1": 2.07,
      "odds2": 1.7,
      "tour": "ATP"
    },
    {
      "tournament": "Granby challenger",
      "time": "01:55",
      "player1": "Boulais J.",
      "player2": "Zhang Z. (6)",
      "odds1": 3.41,
      "odds2": 1.29,
      "tour": "ATP"
    },
    {
      "tournament": "Granby challenger",
      "time": "02:00",
      "player1": "Arseneault N.",
      "player2": "Martin A.",
      "odds1": 2.8,
      "odds2": 1.4,
      "tour": "ATP"
    },
    {
      "tournament": "Granby challenger",
      "time": "02:15",
      "player1": "Shimizu Y.",
      "player2": "Friend J.",
      "odds1": 2.22,
      "odds2": 1.61,
      "tour": "ATP"
    },
    {
      "tournament": "Lincoln challenger",
      "time": "02:55",
      "player1": "Wolf J.",
      "player2": "Fenty A.",
      "odds1": 1.24,
      "odds2": 3.78,
      "tour": "ATP"
    },
    {
      "tournament": "Granby challenger",
      "time": "03:45",
      "player1": "Vukic A. (1)",
      "player2": "Broady L.",
      "odds1": 2.18,
      "odds2": 1.63,
      "tour": "ATP"
    },
    {
      "tournament": "Cordenons challenger",
      "time": "10:00",
      "player1": "Nagal S. (3)",
      "player2": "Cretu C.",
      "odds1": 1.86,
      "odds2": 1.87,
      "tour": "ATP"
    },
    {
      "tournament": "Cordenons challenger",
      "time": "10:00",
      "player1": "Guillen Meza A.",
      "player2": "Bondioli F.",
      "odds1": 1.95,
      "odds2": 1.77,
      "tour": "ATP"
    },
    {
      "tournament": "Cordenons challenger",
      "time": "10:00",
      "player1": "Alcala Gurri M. (5)",
      "player2": "Tabacco G.",
      "odds1": 1.16,
      "odds2": 4.77,
      "tour": "ATP"
    },
    {
      "tournament": "Pozoblanco challenger",
      "time": "10:00",
      "player1": "Perez Navarro P.",
      "player2": "Crawford O. (5)",
      "odds1": 10.64,
      "odds2": 1.03,
      "tour": "ATP"
    },
    {
      "tournament": "Pozoblanco challenger",
      "time": "10:00",
      "player1": "Erel Y.",
      "player2": "Pavlovic L. (3)",
      "odds1": 1.82,
      "odds2": 1.76,
      "tour": "ATP"
    },
    {
      "tournament": "Pozoblanco challenger",
      "time": "10:00",
      "player1": "Castelnuovo L.",
      "player2": "Ghibaudo A.",
      "odds1": 2.47,
      "odds2": 1.49,
      "tour": "ATP"
    },
    {
      "tournament": "Gstaad",
      "time": "10:30",
      "player1": "Martinez P.",
      "player2": "Hanfmann Y.",
      "odds1": 3.6,
      "odds2": 1.29,
      "tour": "ATP"
    },
    {
      "tournament": "Gstaad",
      "time": "10:30",
      "player1": "Cerundolo J. (6)",
      "player2": "Kolar Z.",
      "odds1": 1.26,
      "odds2": 3.8,
      "tour": "ATP"
    },
    {
      "tournament": "Bunschoten challenger",
      "time": "10:30",
      "player1": "Boscardin Dias P.",
      "player2": "Coppejans K. (6)",
      "odds1": 3.04,
      "odds2": 1.34,
      "tour": "ATP"
    },
    {
      "tournament": "Bunschoten challenger",
      "time": "10:30",
      "player1": "Galan D.",
      "player2": "Forger A.",
      "odds1": 1.31,
      "odds2": 3.19,
      "tour": "ATP"
    },
    {
      "tournament": "Bunschoten challenger",
      "time": "10:30",
      "player1": "Clarke J.",
      "player2": "Wessels L.",
      "odds1": 1.26,
      "odds2": 3.61,
      "tour": "ATP"
    },
    {
      "tournament": "Rome 2 WTA",
      "time": "10:30",
      "player1": "Riera J.",
      "player2": "Semenistaja D. (2)",
      "odds1": 2.31,
      "odds2": 1.58,
      "tour": "WTA"
    },
    {
      "tournament": "Rome 2 WTA",
      "time": "10:30",
      "player1": "Kovinic D.",
      "player2": "Basiletti N.",
      "odds1": 2.7,
      "odds2": 1.44,
      "tour": "WTA"
    },
    {
      "tournament": "Bastad",
      "time": "11:00",
      "player1": "Budkov Kjaer N.",
      "player2": "Pellegrino A.",
      "odds1": 1.94,
      "odds2": 1.84,
      "tour": "ATP"
    },
    {
      "tournament": "Bastad",
      "time": "11:00",
      "player1": "Ofner S.",
      "player2": "Tirante T. (7)",
      "odds1": 2.22,
      "odds2": 1.65,
      "tour": "ATP"
    },
    {
      "tournament": "Iasi WTA",
      "time": "11:00",
      "player1": "Quevedo K.",
      "player2": "Ruse E. (6)",
      "odds1": 2.92,
      "odds2": 1.39,
      "tour": "WTA"
    },
    {
      "tournament": "Iasi WTA",
      "time": "11:00",
      "player1": "Arango E.",
      "player2": "Zidansek T.",
      "odds1": 1.76,
      "odds2": 2.04,
      "tour": "WTA"
    },
    {
      "tournament": "Iasi WTA",
      "time": "11:00",
      "player1": "Avanesyan E.",
      "player2": "Uchijima M.",
      "odds1": 1.73,
      "odds2": 2.08,
      "tour": "WTA"
    },
    {
      "tournament": "Kitzbühel WTA",
      "time": "11:00",
      "player1": "Bassols Ribera M. (5)",
      "player2": "Friedsam A.",
      "odds1": 1.36,
      "odds2": 2.99,
      "tour": "WTA"
    },
    {
      "tournament": "Kitzbühel WTA",
      "time": "11:00",
      "player1": "Hennemann C.",
      "player2": "Kraus S. (2)",
      "odds1": 4.39,
      "odds2": 1.19,
      "tour": "WTA"
    },
    {
      "tournament": "Kitzbühel WTA",
      "time": "11:05",
      "player1": "Colmegna M.",
      "player2": "Palicova B.",
      "odds1": 2.93,
      "odds2": 1.37,
      "tour": "WTA"
    },
    {
      "tournament": "Cordenons challenger",
      "time": "11:30",
      "player1": "Martin Manzano J.",
      "player2": "Mayot H. (2)",
      "odds1": 2.45,
      "odds2": 1.5,
      "tour": "ATP"
    },
    {
      "tournament": "Cordenons challenger",
      "time": "11:30",
      "player1": "Villanueva G.",
      "player2": "Ribecai M.",
      "odds1": 2.23,
      "odds2": 1.6,
      "tour": "ATP"
    },
    {
      "tournament": "Cordenons challenger",
      "time": "11:30",
      "player1": "Kravchenko G.",
      "player2": "Torres J.",
      "odds1": 2.11,
      "odds2": 1.67,
      "tour": "ATP"
    },
    {
      "tournament": "Bastad",
      "time": "12:00",
      "player1": "Diaz Acosta F.",
      "player2": "Midon L.",
      "odds1": 1.24,
      "odds2": 3.96,
      "tour": "ATP"
    },
    {
      "tournament": "Bastad",
      "time": "12:00",
      "player1": "Vallejo A.",
      "player2": "Damas M.",
      "odds1": 1.19,
      "odds2": 4.58,
      "tour": "ATP"
    },
    {
      "tournament": "Gstaad",
      "time": "12:00",
      "player1": "Kym J.",
      "player2": "Dietrich D.",
      "odds1": 1.55,
      "odds2": 2.4,
      "tour": "ATP"
    },
    {
      "tournament": "Bunschoten challenger",
      "time": "12:00",
      "player1": "Brunold M.",
      "player2": "Nijboer R.",
      "odds1": 1.81,
      "odds2": 1.9,
      "tour": "ATP"
    },
    {
      "tournament": "Bunschoten challenger",
      "time": "12:00",
      "player1": "Den Ouden G.",
      "player2": "Yevseyev D.",
      "odds1": 1.12,
      "odds2": 5.64,
      "tour": "ATP"
    },
    {
      "tournament": "Bunschoten challenger",
      "time": "12:00",
      "player1": "Gentzsch T. (5)",
      "player2": "Petkovic M.",
      "odds1": 1.52,
      "odds2": 2.41,
      "tour": "ATP"
    },
    {
      "tournament": "Bastad",
      "time": "12:30",
      "player1": "Svrcina D.",
      "player2": "Dimitrov G.",
      "odds1": 2.53,
      "odds2": 1.51,
      "tour": "ATP"
    },
    {
      "tournament": "Bastad",
      "time": "12:30",
      "player1": "Van De Zandschulp B. (6)",
      "player2": "Daniel T.",
      "odds1": 1.61,
      "odds2": 2.28,
      "tour": "ATP"
    },
    {
      "tournament": "Iasi WTA",
      "time": "12:30",
      "player1": "Sherif M.",
      "player2": "Galfi D.",
      "odds1": 1.61,
      "odds2": 2.28,
      "tour": "WTA"
    },
    {
      "tournament": "Iasi WTA",
      "time": "12:30",
      "player1": "Putintseva Y. (9)",
      "player2": "Liu C.",
      "odds1": 1.67,
      "odds2": 2.16,
      "tour": "WTA"
    },
    {
      "tournament": "Iasi WTA",
      "time": "12:30",
      "player1": "Salkova D.",
      "player2": "Ibragimova A.",
      "odds1": 1.66,
      "odds2": 2.17,
      "tour": "WTA"
    },
    {
      "tournament": "Kitzbühel WTA",
      "time": "12:30",
      "player1": "Barthel M.",
      "player2": "Koller A.",
      "odds1": 1.05,
      "odds2": 8.85,
      "tour": "WTA"
    },
    {
      "tournament": "Kitzbühel WTA",
      "time": "12:30",
      "player1": "Pigossi L.",
      "player2": "Samson L. (6)",
      "odds1": 4.0,
      "odds2": 1.22,
      "tour": "WTA"
    },
    {
      "tournament": "Kitzbühel WTA",
      "time": "12:30",
      "player1": "Carle M.",
      "player2": "Von Deichmann K.",
      "odds1": 1.33,
      "odds2": 3.18,
      "tour": "WTA"
    },
    {
      "tournament": "Cordenons challenger",
      "time": "13:00",
      "player1": "Mrva M.",
      "player2": "Caniato C.",
      "odds1": 1.63,
      "odds2": 2.16,
      "tour": "ATP"
    },
    {
      "tournament": "Cordenons challenger",
      "time": "13:00",
      "player1": "Roncadelli F.",
      "player2": "Giustino L. (4)",
      "odds1": 2.05,
      "odds2": 1.7,
      "tour": "ATP"
    },
    {
      "tournament": "Cordenons challenger",
      "time": "13:00",
      "player1": "Fuele M.",
      "player2": "Prihodko O.",
      "odds1": 2.98,
      "odds2": 1.35,
      "tour": "ATP"
    },
    {
      "tournament": "Bastad",
      "time": "13:30",
      "player1": "Choinski J.",
      "player2": "Basilashvili N.",
      "odds1": 1.57,
      "odds2": 2.37,
      "tour": "ATP"
    },
    {
      "tournament": "Bastad",
      "time": "13:30",
      "player1": "Travaglia S.",
      "player2": "Krumich M.",
      "odds1": 2.1,
      "odds2": 1.72,
      "tour": "ATP"
    },
    {
      "tournament": "Gstaad",
      "time": "13:30",
      "player1": "Cina F.",
      "player2": "Halys Q.",
      "odds1": 1.95,
      "odds2": 1.83,
      "tour": "ATP"
    },
    {
      "tournament": "Bunschoten challenger",
      "time": "13:30",
      "player1": "Barton H.",
      "player2": "Reis Da Silva J. (8)",
      "odds1": 1.51,
      "odds2": 2.41,
      "tour": "ATP"
    },
    {
      "tournament": "Bunschoten challenger",
      "time": "13:30",
      "player1": "Squire H. (7)",
      "player2": "Kumstat J.",
      "odds1": 1.49,
      "odds2": 2.49,
      "tour": "ATP"
    },
    {
      "tournament": "Bastad",
      "time": "14:00",
      "player1": "Borges N. (5)",
      "player2": "Kouame M.",
      "odds1": 1.29,
      "odds2": 3.53,
      "tour": "ATP"
    },
    {
      "tournament": "Bastad",
      "time": "14:00",
      "player1": "Altmaier D.",
      "player2": "Gaston H.",
      "odds1": 1.61,
      "odds2": 2.28,
      "tour": "ATP"
    },
    {
      "tournament": "Iasi WTA",
      "time": "14:00",
      "player1": "Oliynykova O. (3)",
      "player2": "Oz I.",
      "odds1": 1.21,
      "odds2": 4.31,
      "tour": "WTA"
    },
    {
      "tournament": "Iasi WTA",
      "time": "14:00",
      "player1": "Bulgaru M.",
      "player2": "Pridankina E.",
      "odds1": 4.37,
      "odds2": 1.2,
      "tour": "WTA"
    },
    {
      "tournament": "Kitzbühel WTA",
      "time": "14:00",
      "player1": "Wolff V.",
      "player2": "Vandromme J. (7)",
      "odds1": 4.15,
      "odds2": 1.21,
      "tour": "WTA"
    },
    {
      "tournament": "Kitzbühel WTA",
      "time": "14:00",
      "player1": "Rabl L.",
      "player2": "Rus A.",
      "odds1": 12.89,
      "odds2": 1.02,
      "tour": "WTA"
    },
    {
      "tournament": "Cordenons challenger",
      "time": "14:30",
      "player1": "Dellien H. (1)",
      "player2": "Xilas I.",
      "odds1": 1.17,
      "odds2": 4.7,
      "tour": "ATP"
    },
    {
      "tournament": "Cordenons challenger",
      "time": "14:30",
      "player1": "Makk P.",
      "player2": "Seyboth Wild T. (8)",
      "odds1": 4.07,
      "odds2": 1.21,
      "tour": "ATP"
    },
    {
      "tournament": "Gstaad",
      "time": "15:00",
      "player1": "Muller A.",
      "player2": "Shevchenko A.",
      "odds1": 2.49,
      "odds2": 1.52,
      "tour": "ATP"
    },
    {
      "tournament": "Gstaad",
      "time": "15:00",
      "player1": "Tsitsipas S.",
      "player2": "Buse I. (5)",
      "odds1": 2.16,
      "odds2": 1.68,
      "tour": "ATP"
    },
    {
      "tournament": "Bunschoten challenger",
      "time": "15:00",
      "player1": "Barrios Vera M. (1)",
      "player2": "Visker N.",
      "odds1": 1.14,
      "odds2": 5.01,
      "tour": "ATP"
    },
    {
      "tournament": "Bunschoten challenger",
      "time": "15:00",
      "player1": "Broska F.",
      "player2": "Bar Biryukov P.",
      "odds1": 1.24,
      "odds2": 3.8,
      "tour": "ATP"
    },
    {
      "tournament": "Bunschoten challenger",
      "time": "15:00",
      "player1": "Martineau M.",
      "player2": "Campana Lee G.",
      "odds1": 1.95,
      "odds2": 1.77,
      "tour": "ATP"
    },
    {
      "tournament": "Bastad",
      "time": "15:30",
      "player1": "Dahlin M.",
      "player2": "Baez S. (8)",
      "odds1": 14.6,
      "odds2": 1.02,
      "tour": "ATP"
    },
    {
      "tournament": "Iasi WTA",
      "time": "15:30",
      "player1": "Udvardy P. (5)",
      "player2": "Romero Gormaz L.",
      "odds1": 1.8,
      "odds2": 1.98,
      "tour": "WTA"
    },
    {
      "tournament": "Umag",
      "time": "16:00",
      "player1": "Dodig M.",
      "player2": "Carreno-Busta P.",
      "odds1": 3.0,
      "odds2": 1.38,
      "tour": "ATP"
    },
    {
      "tournament": "Umag",
      "time": "16:00",
      "player1": "Molcan A.",
      "player2": "Royer V.",
      "odds1": 1.57,
      "odds2": 2.36,
      "tour": "ATP"
    },
    {
      "tournament": "Umag",
      "time": "16:00",
      "player1": "Topo M.",
      "player2": "Ugo Carabelli C. (7)",
      "odds1": 2.99,
      "odds2": 1.38,
      "tour": "ATP"
    },
    {
      "tournament": "Granby challenger",
      "time": "16:00",
      "player1": "Glinka D. (7)",
      "player2": "Johns G.",
      "odds1": 1.46,
      "odds2": 2.34,
      "tour": "ATP"
    },
    {
      "tournament": "Rome 2 WTA",
      "time": "16:00",
      "player1": "Ferro F.",
      "player2": "Zantedeschi A.",
      "odds1": 1.47,
      "odds2": 2.56,
      "tour": "WTA"
    },
    {
      "tournament": "Rome 2 WTA",
      "time": "16:00",
      "player1": "Kostovic T.",
      "player2": "Ruggeri J.",
      "odds1": 1.32,
      "odds2": 2.97,
      "tour": "WTA"
    },
    {
      "tournament": "Iasi WTA",
      "time": "16:30",
      "player1": "Badosa P.",
      "player2": "Kalinina A. (4)",
      "odds1": 1.58,
      "odds2": 2.33,
      "tour": "WTA"
    },
    {
      "tournament": "Athens WTA",
      "time": "16:30",
      "player1": "Krejcikova B. (3)",
      "player2": "Tomova V.",
      "odds1": 1.08,
      "odds2": 7.79,
      "tour": "WTA"
    },
    {
      "tournament": "Athens WTA",
      "time": "16:30",
      "player1": "Monnet C.",
      "player2": "Masarova R.",
      "odds1": 5.1,
      "odds2": 1.16,
      "tour": "WTA"
    },
    {
      "tournament": "Athens WTA",
      "time": "16:30",
      "player1": "Ito A.",
      "player2": "Korneeva A.",
      "odds1": 4.47,
      "odds2": 1.2,
      "tour": "WTA"
    },
    {
      "tournament": "Lincoln challenger",
      "time": "17:00",
      "player1": "Smith C. (6)",
      "player2": "Ilagan A.",
      "odds1": 1.27,
      "odds2": 3.13,
      "tour": "ATP"
    },
    {
      "tournament": "Iasi WTA",
      "time": "17:00",
      "player1": "Kawa K.",
      "player2": "Waltert S.",
      "odds1": 2.73,
      "odds2": 1.44,
      "tour": "WTA"
    },
    {
      "tournament": "Gstaad",
      "time": "17:30",
      "player1": "Faria J.",
      "player2": "Wawrinka S.",
      "odds1": 1.47,
      "odds2": 2.65,
      "tour": "ATP"
    },
    {
      "tournament": "Umag",
      "time": "17:30",
      "player1": "Gomez F.",
      "player2": "McDonald N.",
      "odds1": 1.77,
      "odds2": 2.02,
      "tour": "ATP"
    },
    {
      "tournament": "Granby challenger",
      "time": "17:30",
      "player1": "Uchida K.",
      "player2": "Galarneau A. (8)",
      "odds1": 4.78,
      "odds2": 1.15,
      "tour": "ATP"
    },
    {
      "tournament": "Granby challenger",
      "time": "17:30",
      "player1": "Holmgren A. (3)",
      "player2": "Watanuki Y.",
      "odds1": 1.83,
      "odds2": 1.91,
      "tour": "ATP"
    },
    {
      "tournament": "Rome 2 WTA",
      "time": "17:30",
      "player1": "Trevisan M.",
      "player2": "Grant T. (8)",
      "odds1": 3.22,
      "odds2": 1.3,
      "tour": "WTA"
    },
    {
      "tournament": "Rome 2 WTA",
      "time": "17:30",
      "player1": "Brancaccio N. (7)",
      "player2": "Pieri J.",
      "odds1": 1.24,
      "odds2": 3.59,
      "tour": "WTA"
    },
    {
      "tournament": "Umag",
      "time": "18:00",
      "player1": "Sesko Z.",
      "player2": "Merida Aguilar D.",
      "odds1": 5.61,
      "odds2": 1.14,
      "tour": "ATP"
    },
    {
      "tournament": "Umag",
      "time": "18:00",
      "player1": "Cecchinato M.",
      "player2": "Burruchaga R.",
      "odds1": 2.2,
      "odds2": 1.66,
      "tour": "ATP"
    },
    {
      "tournament": "Bunschoten challenger",
      "time": "18:00",
      "player1": "Boogaard T.",
      "player2": "Onclin G. (2)",
      "odds1": 3.67,
      "odds2": 1.23,
      "tour": "ATP"
    },
    {
      "tournament": "Iasi WTA",
      "time": "18:00",
      "player1": "Amariei I.",
      "player2": "Jacquemot E. (8)",
      "odds1": 5.14,
      "odds2": 1.15,
      "tour": "WTA"
    },
    {
      "tournament": "Athens WTA",
      "time": "18:00",
      "player1": "Blinkova A.",
      "player2": "Sasnovich A.",
      "odds1": 2.04,
      "odds2": 1.76,
      "tour": "WTA"
    },
    {
      "tournament": "Athens WTA",
      "time": "18:00",
      "player1": "Sakellaridi S.",
      "player2": "Tona M.",
      "odds1": 1.59,
      "odds2": 2.31,
      "tour": "WTA"
    },
    {
      "tournament": "Pozoblanco challenger",
      "time": "18:30",
      "player1": "Zhou Y. (7)",
      "player2": "Kozlov S.",
      "odds1": 1.51,
      "odds2": 2.26,
      "tour": "ATP"
    },
    {
      "tournament": "Athens WTA",
      "time": "18:30",
      "player1": "Tauson C. (1)",
      "player2": "Hibino N.",
      "odds1": 1.25,
      "odds2": 3.89,
      "tour": "WTA"
    },
    {
      "tournament": "Granby challenger",
      "time": "19:00",
      "player1": "Cassone M.",
      "player2": "Schoolkate T. (4)",
      "odds1": 2.12,
      "odds2": 1.55,
      "tour": "ATP"
    },
    {
      "tournament": "Cordenons challenger",
      "time": "19:00",
      "player1": "Nedic A.",
      "player2": "Dalla Valle E.",
      "odds1": 1.88,
      "odds2": 1.79,
      "tour": "ATP"
    },
    {
      "tournament": "Rome 2 WTA",
      "time": "19:00",
      "player1": "Pace F.",
      "player2": "Vedder E.",
      "odds1": 4.35,
      "odds2": 1.18,
      "tour": "WTA"
    },
    {
      "tournament": "Rome 2 WTA",
      "time": "19:00",
      "player1": "Mazzola A.",
      "player2": "Bronzetti L. (4)",
      "odds1": 3.56,
      "odds2": 1.26,
      "tour": "WTA"
    },
    {
      "tournament": "Umag",
      "time": "19:30",
      "player1": "Marozsan F. (6)",
      "player2": "Prado Angelo J.",
      "odds1": 1.33,
      "odds2": 3.29,
      "tour": "ATP"
    },
    {
      "tournament": "Athens WTA",
      "time": "19:30",
      "player1": "Valentova T. (7)",
      "player2": "Costoulas S.",
      "odds1": 1.19,
      "odds2": 4.65,
      "tour": "WTA"
    },
    {
      "tournament": "Lincoln challenger",
      "time": "20:00",
      "player1": "Johnson S.",
      "player2": "Bertola R. (7)",
      "odds1": 1.84,
      "odds2": 1.73,
      "tour": "ATP"
    },
    {
      "tournament": "Lincoln challenger",
      "time": "20:00",
      "player1": "Lajal M. (5)",
      "player2": "Svajda T.",
      "odds1": 1.5,
      "odds2": 2.17,
      "tour": "ATP"
    },
    {
      "tournament": "Granby challenger",
      "time": "20:30",
      "player1": "Sun F.",
      "player2": "Gea A. (2)",
      "odds1": 4.24,
      "odds2": 1.18,
      "tour": "ATP"
    },
    {
      "tournament": "Athens WTA",
      "time": "20:30",
      "player1": "Timofeeva M.",
      "player2": "Li A. (2)",
      "odds1": 2.21,
      "odds2": 1.64,
      "tour": "WTA"
    },
    {
      "tournament": "Umag",
      "time": "21:00",
      "player1": "Droguet T.",
      "player2": "Blockx A. (5)",
      "odds1": 2.38,
      "odds2": 1.56,
      "tour": "ATP"
    },
    {
      "tournament": "Lincoln challenger",
      "time": "21:30",
      "player1": "Imamura M.",
      "player2": "McCabe J.",
      "odds1": 2.38,
      "odds2": 1.46,
      "tour": "ATP"
    },
    {
      "tournament": "Granby challenger",
      "time": "22:00",
      "player1": "Milavsky D.",
      "player2": "Chan D.",
      "odds1": 1.6,
      "odds2": 2.03,
      "tour": "ATP"
    }
  ]
}