{
  "last_updated": "2026-03-28T02:23:25.498658",
  "count": 17,
  "matches": [
    {
      "tournament": "Miami",
      "time": "00:10",
      "player1": "Sinner J. (2)",
      "player2": "Zverev A. (3)",
      "odds1": 1.14,
      "odds2": 5.58,
      "tour": "ATP"
    },
    {
      "tournament": "Morelia challenger",
      "time": "01:15",
      "player1": "Gojo B. (8)",
      "player2": "Mejia N.",
      "odds1": 1.41,
      "odds2": 2.77,
      "tour": "ATP"
    },
    {
      "tournament": "Yokkaichi challenger",
      "time": "04:00",
      "player1": "Noguchi R. (7)",
      "player2": "Wendelken H.",
      "odds1": 2.1,
      "odds2": 1.68,
      "tour": "ATP"
    },
    {
      "tournament": "Yokkaichi challenger",
      "time": "04:30",
      "player1": "Uchiyama Y.",
      "player2": "Matsuoka H.",
      "odds1": 1.45,
      "odds2": 2.62,
      "tour": "ATP"
    },
    {
      "tournament": "Alicante challenger",
      "time": "11:00",
      "player1": "Ofner S. (1)",
      "player2": "Carreno-Busta P. (5)",
      "odds1": 1.64,
      "odds2": 2.16,
      "tour": "ATP"
    },
    {
      "tournament": "Split challenger",
      "time": "11:00",
      "player1": "Gueymard Wayenburg S.",
      "player2": "Gentzsch T. (7)",
      "odds1": 1.76,
      "odds2": 1.96,
      "tour": "ATP"
    },
    {
      "tournament": "Alicante challenger",
      "time": "12:30",
      "player1": "Safiullin R.",
      "player2": "Llamas Ruiz P.",
      "odds1": 2.39,
      "odds2": 1.54,
      "tour": "ATP"
    },
    {
      "tournament": "Split challenger",
      "time": "12:30",
      "player1": "Poljicak M.",
      "player2": "Coppejans K. (6)",
      "odds1": 2.21,
      "odds2": 1.61,
      "tour": "ATP"
    },
    {
      "tournament": "Dubrovník",
      "time": "13:00",
      "player1": "Lazaro Garcia A.",
      "player2": "Sherif M. (3)",
      "odds1": 2.14,
      "odds2": 1.66,
      "tour": "WTA"
    },
    {
      "tournament": "Dubrovník",
      "time": "13:00",
      "player1": "Kalinina A. (7)",
      "player2": "Zidansek T.",
      "odds1": 1.35,
      "odds2": 3.07,
      "tour": "WTA"
    },
    {
      "tournament": "Neapol challenger",
      "time": "14:00",
      "player1": "Medjedovic H. (5)",
      "player2": "Sachko V.",
      "odds1": 1.26,
      "odds2": 3.66,
      "tour": "ATP"
    },
    {
      "tournament": "Neapol challenger",
      "time": "15:30",
      "player1": "Altmaier D. (1)",
      "player2": "Bondioli F.",
      "odds1": 1.32,
      "odds2": 3.21,
      "tour": "ATP"
    },
    {
      "tournament": "Sao Paulo 2 challenger",
      "time": "19:00",
      "player1": "Burruchaga R. (3)",
      "player2": "Prado Angelo J. (8)",
      "odds1": 1.28,
      "odds2": 2.91,
      "tour": "ATP"
    },
    {
      "tournament": "Miami",
      "time": "20:00",
      "player1": "Sabalenka A. (1)",
      "player2": "Gauff C. (4)",
      "odds1": 1.35,
      "odds2": 3.2,
      "tour": "WTA"
    },
    {
      "tournament": "Sao Paulo 2 challenger",
      "time": "21:00",
      "player1": "Faria J. (5)",
      "player2": "Dellien H. (6)",
      "odds1": 1.03,
      "odds2": 1.03,
      "tour": "ATP"
    },
    {
      "tournament": "Bucaramanga challenger",
      "time": "21:00",
      "player1": "Justo G. (1)",
      "player2": "Soto M. (2)",
      "odds1": 1.45,
      "odds2": 2.37,
      "tour": "ATP"
    },
    {
      "tournament": "Miami",
      "time": "",
      "player1": "Brady J.",
      "player2": "Stephens S.",
      "odds1": null,
      "odds2": null,
      "tour": "WTA"
    }
  ]
}