{
  "last_updated": "2026-07-03T09:19:14.039221",
  "count": 34,
  "matches": [
    {
      "tournament": "Brasov challenger",
      "time": "10:10",
      "player1": "Nedic A.",
      "player2": "Smith K.",
      "odds1": 1.34,
      "odds2": 3.1,
      "tour": "ATP"
    },
    {
      "tournament": "Brasov challenger",
      "time": "10:10",
      "player1": "Justo G.",
      "player2": "Wallin O.",
      "odds1": 1.56,
      "odds2": 2.32,
      "tour": "ATP"
    },
    {
      "tournament": "Troyes challenger",
      "time": "10:10",
      "player1": "Giustino L. (1)",
      "player2": "Marcondes I.",
      "odds1": 1.86,
      "odds2": 1.86,
      "tour": "ATP"
    },
    {
      "tournament": "Milan challenger",
      "time": "10:15",
      "player1": "Heide G. (5)",
      "player2": "Dalla Valle E.",
      "odds1": 1.37,
      "odds2": 2.92,
      "tour": "ATP"
    },
    {
      "tournament": "Brasov challenger",
      "time": "11:30",
      "player1": "Gueymard Wayenburg S.",
      "player2": "Kasnikowski M.",
      "odds1": 2.43,
      "odds2": 1.51,
      "tour": "ATP"
    },
    {
      "tournament": "Brasov challenger",
      "time": "11:30",
      "player1": "Kuzmanov D.",
      "player2": "Piros Z. (2)",
      "odds1": 3.09,
      "odds2": 1.34,
      "tour": "ATP"
    },
    {
      "tournament": "Milan challenger",
      "time": "11:35",
      "player1": "Diaz Acosta F. (3)",
      "player2": "Martin Manzano J.",
      "odds1": 1.13,
      "odds2": 5.48,
      "tour": "ATP"
    },
    {
      "tournament": "Milan challenger",
      "time": "11:45",
      "player1": "Basile P.",
      "player2": "Cecchinato M.",
      "odds1": 2.7,
      "odds2": 1.43,
      "tour": "ATP"
    },
    {
      "tournament": "Troyes challenger",
      "time": "11:45",
      "player1": "Feldbausch K. (3)",
      "player2": "Montes-De La Torre I. (8)",
      "odds1": 1.75,
      "odds2": 1.99,
      "tour": "ATP"
    },
    {
      "tournament": "Wimbledon",
      "time": "12:00",
      "player1": "Safiullin R.",
      "player2": "Fonseca J. (24)",
      "odds1": 3.61,
      "odds2": 1.29,
      "tour": "ATP"
    },
    {
      "tournament": "Wimbledon",
      "time": "12:00",
      "player1": "Bencic B. (11)",
      "player2": "Kalinskaya A. (19)",
      "odds1": 1.34,
      "odds2": 3.27,
      "tour": "WTA"
    },
    {
      "tournament": "Troyes challenger",
      "time": "13:15",
      "player1": "Moeller M.",
      "player2": "Sharipov M.",
      "odds1": 2.04,
      "odds2": 1.72,
      "tour": "ATP"
    },
    {
      "tournament": "Wimbledon",
      "time": "13:30",
      "player1": "Jodar R. (23)",
      "player2": "Mochizuki S.",
      "odds1": 1.3,
      "odds2": 3.51,
      "tour": "ATP"
    },
    {
      "tournament": "Wimbledon",
      "time": "13:30",
      "player1": "Struff J.",
      "player2": "Medvedev D. (8)",
      "odds1": 4.89,
      "odds2": 1.18,
      "tour": "ATP"
    },
    {
      "tournament": "Wimbledon",
      "time": "13:30",
      "player1": "Alexandrova E. (18)",
      "player2": "Jovic I. (16)",
      "odds1": 2.66,
      "odds2": 1.48,
      "tour": "WTA"
    },
    {
      "tournament": "Milan challenger",
      "time": "14:00",
      "player1": "Comesana F. (1)",
      "player2": "Rincon D.",
      "odds1": 1.3,
      "odds2": 3.39,
      "tour": "ATP"
    },
    {
      "tournament": "Wimbledon",
      "time": "14:00",
      "player1": "Kasatkina D.",
      "player2": "Osaka N. (14)",
      "odds1": 4.53,
      "odds2": 1.2,
      "tour": "WTA"
    },
    {
      "tournament": "Wimbledon",
      "time": "14:00",
      "player1": "Pegula J. (4)",
      "player2": "Bouzas Maneiro J.",
      "odds1": 1.11,
      "odds2": 6.7,
      "tour": "WTA"
    },
    {
      "tournament": "Wimbledon",
      "time": "14:30",
      "player1": "Rinderknech A. (25)",
      "player2": "Djokovic N. (7)",
      "odds1": 7.18,
      "odds2": 1.1,
      "tour": "ATP"
    },
    {
      "tournament": "Wimbledon",
      "time": "15:00",
      "player1": "Davidovich Fokina A. (22)",
      "player2": "Fucsovics M.",
      "odds1": 1.27,
      "odds2": 3.84,
      "tour": "ATP"
    },
    {
      "tournament": "Cary challenger",
      "time": "15:00",
      "player1": "Kennedy J.",
      "player2": "Watanuki Y.",
      "odds1": 2.62,
      "odds2": 1.45,
      "tour": "ATP"
    },
    {
      "tournament": "Cary challenger",
      "time": "15:00",
      "player1": "Friend J.",
      "player2": "Shick B.",
      "odds1": 1.45,
      "odds2": 2.61,
      "tour": "ATP"
    },
    {
      "tournament": "Wimbledon",
      "time": "15:30",
      "player1": "Hurkacz H.",
      "player2": "Paul T. (21)",
      "odds1": 2.46,
      "odds2": 1.55,
      "tour": "ATP"
    },
    {
      "tournament": "Wimbledon",
      "time": "15:30",
      "player1": "Sinner J. (1)",
      "player2": "Brooksby J.",
      "odds1": 1.02,
      "odds2": 16.26,
      "tour": "ATP"
    },
    {
      "tournament": "Wimbledon",
      "time": "15:30",
      "player1": "Muchova K. (10)",
      "player2": "Sawangkaew M.",
      "odds1": 1.08,
      "odds2": 8.1,
      "tour": "WTA"
    },
    {
      "tournament": "Wimbledon",
      "time": "15:30",
      "player1": "Bartunkova N.",
      "player2": "Krejcikova B.",
      "odds1": 2.48,
      "odds2": 1.54,
      "tour": "WTA"
    },
    {
      "tournament": "Wimbledon",
      "time": "16:30",
      "player1": "Sabalenka A. (1)",
      "player2": "Ostapenko J.",
      "odds1": 1.27,
      "odds2": 3.83,
      "tour": "WTA"
    },
    {
      "tournament": "Quito challenger",
      "time": "17:00",
      "player1": "Casanova H. (7)",
      "player2": "Osorio J.",
      "odds1": 1.17,
      "odds2": 4.61,
      "tour": "ATP"
    },
    {
      "tournament": "Quito challenger",
      "time": "17:00",
      "player1": "Meligeni Rodrigues Alv",
      "player2": "Pacheco Mendez R. (4)",
      "odds1": 1.78,
      "odds2": 1.95,
      "tour": "ATP"
    },
    {
      "tournament": "Troyes challenger",
      "time": "17:30",
      "player1": "Coulibaly E.",
      "player2": "Hemery C. (4)",
      "odds1": 2.45,
      "odds2": 1.51,
      "tour": "ATP"
    },
    {
      "tournament": "Wimbledon",
      "time": "17:30",
      "player1": "Liu C.",
      "player2": "Gauff C. (7)",
      "odds1": 6.87,
      "odds2": 1.11,
      "tour": "WTA"
    },
    {
      "tournament": "Wimbledon",
      "time": "18:00",
      "player1": "Auger Aliassime F. (3)",
      "player2": "Zheng M.",
      "odds1": 1.17,
      "odds2": 4.99,
      "tour": "ATP"
    },
    {
      "tournament": "Quito challenger",
      "time": "18:30",
      "player1": "Magadan A.",
      "player2": "Pucinelli De Almeida M. (8)",
      "odds1": 4.07,
      "odds2": 1.21,
      "tour": "ATP"
    },
    {
      "tournament": "Quito challenger",
      "time": "18:30",
      "player1": "Monzon I.",
      "player2": "Heredia S.",
      "odds1": 2.06,
      "odds2": 1.7,
      "tour": "ATP"
    }
  ]
}